{
  "primary": {
    "50": "#f7f7f8",
    "100": "#ebedef",
    "200": "#d7dbdf",
    "300": "#bac0ca",
    "400": "#8e9bae",
    "500": "#687b97",
    "600": "#475569",
    "700": "#4e5e74",
    "800": "#3f4a5a",
    "900": "#2f3741",
    "950": "#1f2329"
  },
  "navy": {
    "800": "#33373e",
    "900": "#232629",
    "950": "#18191b"
  },
  "secondary": "#374151",
  "accent": "#766184",
  "heroGradient": {
    "start": "#131416",
    "mid": "#292d32",
    "end": "#475569"
  },
  "shadow": {
    "r": 71,
    "g": 85,
    "b": 105
  },
  "cssVars": {
    "primary": "rgb(71 85 105)",
    "secondary": "rgb(55 65 81)",
    "accent": "rgb(118 97 132)"
  }
}