[
  {
    "slug": "field-calibrations-inc-phoenix",
    "name": "Field Calibrations, Inc.",
    "city": "Phoenix",
    "state": "AZ",
    "address": "",
    "lat": 33.4484367,
    "lng": -112.074141,
    "phone": "1777219340",
    "website": "https://fieldcal.com",
    "email": "",
    "contact_form_url": "",
    "contact_method": "",
    "rating": 0.0,
    "review_count": 0,
    "description": "ISO/IEC 17025:2017 accredited calibration laboratory (CL-112) providing precise calibration services across various disciplines.",
    "certifications": [],
    "services": [
      "ISO 17025 Accredited Calibration"
    ],
    "years_experience": null,
    "coverage_area": "",
    "equipment": [],
    "claimed": false,
    "featured": false,
    "source": "perplexity",
    "scraped_at": "2026-04-26 15:54:50",
    "sentiment": null
  },
  {
    "slug": "michelli-weighing-measurement-phoenix",
    "name": "Michelli Weighing & Measurement",
    "city": "Phoenix",
    "state": "AZ",
    "address": "Roeser Road (off I-10, between S 32nd St & S 40th St), Phoenix, AZ",
    "lat": 33.4484367,
    "lng": -112.074141,
    "phone": "106.1524751",
    "website": "https://www.michelli.com",
    "email": "info@Michelli.com",
    "contact_form_url": "",
    "contact_method": "",
    "rating": 0.0,
    "review_count": 0,
    "description": "Phoenix calibration lab offering weighing and measurement equipment sales, service, rental, standard calibration, and ISO 17025 accredited calibration.",
    "certifications": [],
    "services": [
      "Weighing Equipment Calibration",
      "Measurement Calibration",
      "ISO 17025 Calibration"
    ],
    "years_experience": null,
    "coverage_area": "",
    "equipment": [],
    "claimed": false,
    "featured": false,
    "source": "perplexity",
    "scraped_at": "2026-04-26 15:54:50",
    "sentiment": null
  },
  {
    "slug": "tektronix-phoenix",
    "name": "Tektronix",
    "city": "Phoenix",
    "state": "AZ",
    "address": "2320 West Peoria Avenue, Bldg. D-133, Phoenix, AZ 85029",
    "lat": 33.4484,
    "lng": -112.074,
    "phone": "800-438-8165",
    "website": "https://www.tek.com",
    "email": "tekamericas@tektronix.com",
    "contact_form_url": "",
    "contact_method": "",
    "rating": 0.0,
    "review_count": 0,
    "description": "Global network of calibration labs offering pick-up and delivery service in Phoenix with extensive calibration capabilities.",
    "certifications": [],
    "services": [
      "Instrument Calibration",
      "Pick-up and Delivery"
    ],
    "years_experience": null,
    "coverage_area": "",
    "equipment": [],
    "claimed": false,
    "featured": false,
    "source": "perplexity",
    "scraped_at": "2026-04-26 15:54:50",
    "sentiment": {
      "label": "neutral",
      "score": 0.5,
      "keywords": [],
      "highlights": [],
      "summary": "No customer reviews detected. Content appears to be website UI elements (checkout flow, navigation) rather than customer feedback about Tektronix."
    }
  },
  {
    "slug": "trident-calibration-labs-phoenix",
    "name": "Trident Calibration Labs",
    "city": "Phoenix",
    "state": "AZ",
    "address": "1725 E Robin Ln, Phoenix, AZ 85024",
    "lat": 33.4484,
    "lng": -112.074,
    "phone": "1840629735",
    "website": "https://tridentcalibration.com",
    "email": "contact@tridentcalibration.com",
    "contact_form_url": "",
    "contact_method": "",
    "rating": 0.0,
    "review_count": 0,
    "description": "ISO/IEC 17025 accredited lab offering reliable and cost-effective precision calibration services in the greater Phoenix area.",
    "certifications": [],
    "services": [
      "Accredited Calibration",
      "Precision Calibration"
    ],
    "years_experience": null,
    "coverage_area": "",
    "equipment": [],
    "claimed": false,
    "featured": false,
    "source": "perplexity",
    "scraped_at": "2026-04-26 15:54:50",
    "sentiment": null
  }
]